polarisllm/__init__.py
polarisllm/cli.py
polarisllm/main.py
polarisllm/commands/__init__.py
polarisllm/commands/deploy.py
polarisllm/commands/list_models.py
polarisllm/commands/logs.py
polarisllm/commands/server.py
polarisllm/commands/status.py
polarisllm/commands/stop.py
polarisllm/core/__init__.py
polarisllm/core/config.py
polarisllm/core/log_manager.py
polarisllm/core/port_manager.py
polarisllm/core/process_manager.py
polarisllm/core/registry.py
polarisllm/src/__init__.py
polarisllm/src/api/__init__.py
src/__init__.py
src/api/__init__.py
src/api/dependencies.py
src/api/models.py
src/api/server.py
src/api/routes/__init__.py
src/api/routes/admin.py
src/api/routes/chat.py
src/api/routes/models.py
src/core/__init__.py
src/core/config.py
src/core/model_manager.py
src/core/runtime.py
polarisllm-2.0.5.dist-info/METADATA
polarisllm-2.0.5.dist-info/WHEEL
polarisllm-2.0.5.dist-info/entry_points.txt
polarisllm-2.0.5.dist-info/top_level.txt
polarisllm-2.0.5.dist-info/RECORD
