Metadata-Version: 2.4
Name: polarisllm
Version: 2.0.5
Summary: 🌟 The Ultimate Multi-Model LLM Runtime Platform - Deploy, manage, and serve 300+ language models with OpenAI-compatible APIs. Built on ms-swift for production-ready performance.
Home-page: https://github.com/polarisllm/polarisLLM
Author: PolarisLLM Team
Author-email: elon@polariscloud.ai
Classifier: Development Status :: 4 - Beta
Classifier: Intended Audience :: Developers
Classifier: License :: OSI Approved :: MIT License
Classifier: Operating System :: OS Independent
Classifier: Programming Language :: Python :: 3
Classifier: Programming Language :: Python :: 3.8
Classifier: Programming Language :: Python :: 3.9
Classifier: Programming Language :: Python :: 3.10
Classifier: Programming Language :: Python :: 3.11
Classifier: Topic :: Scientific/Engineering :: Artificial Intelligence
Requires-Python: >=3.8
Requires-Dist: ms-swift
Requires-Dist: fastapi
Requires-Dist: uvicorn[standard]
Requires-Dist: aiohttp
Requires-Dist: pydantic
Requires-Dist: pyyaml
Requires-Dist: psutil
Requires-Dist: python-multipart
Requires-Dist: rich
Requires-Dist: requests
Provides-Extra: dev
Requires-Dist: pytest; extra == "dev"
Requires-Dist: black; extra == "dev"
Requires-Dist: flake8; extra == "dev"
Dynamic: author
Dynamic: author-email
Dynamic: classifier
Dynamic: description
Dynamic: description-content-type
Dynamic: home-page
Dynamic: provides-extra
Dynamic: requires-dist
Dynamic: requires-python
Dynamic: summary
